MANIFEST.in
README.txt
setup.py
etc/configspec.ini
src/mreorg/__init__.py
src/mreorg/config.py
src/mreorg/layouts.py
src/mreorg/scriptflags.py
src/mreorg.egg-info/PKG-INFO
src/mreorg.egg-info/SOURCES.txt
src/mreorg.egg-info/dependency_links.txt
src/mreorg.egg-info/entry_points.txt
src/mreorg.egg-info/requires.txt
src/mreorg.egg-info/top_level.txt
src/mreorg/curator/__init__.py
src/mreorg/curator/manage.py
src/mreorg/curator/settings.py
src/mreorg/curator/urls.py
src/mreorg/curator/backend/__init__.py
src/mreorg/curator/backend/db_writer_hooks.py
src/mreorg/curator/backend/simmgr_backend.py
src/mreorg/curator/cmdline/__init__.py
src/mreorg/curator/cmdline/mreorg_curate.py
src/mreorg/curator/frontend/__init__.py
src/mreorg/curator/frontend/ajax.py
src/mreorg/curator/frontend/dbdata_from_config.py
src/mreorg/curator/frontend/models.py
src/mreorg/curator/frontend/views.py
src/mreorg/curator/frontend/static/customcss/haiku_mod.css
src/mreorg/curator/frontend/static/customcss/style.css
src/mreorg/curator/frontend/static/customcss/images/logo.png
src/mreorg/curator/frontend/static/javascript/builder.js
src/mreorg/curator/frontend/static/javascript/controls.js
src/mreorg/curator/frontend/static/javascript/dragdrop.js
src/mreorg/curator/frontend/static/javascript/effects.js
src/mreorg/curator/frontend/static/javascript/prototype.js
src/mreorg/curator/frontend/static/javascript/scriptaculous.js
src/mreorg/curator/frontend/static/javascript/slider.js
src/mreorg/curator/frontend/static/javascript/sound.js
src/mreorg/curator/frontend/static/javascript/unittest.js
src/mreorg/curator/frontend/static/javascript-moment/moment.js
src/mreorg/curator/frontend/static/sphinx/basic.css
src/mreorg/curator/frontend/static/sphinx/default.css
src/mreorg/curator/frontend/static/sphinx/pygments.css
src/mreorg/curator/frontend/templates/__init__.py
src/mreorg/curator/frontend/templates/base.html
src/mreorg/curator/frontend/templates/configurations.html
src/mreorg/curator/frontend/templates/overview.html
src/mreorg/curator/frontend/templates/simfile_details.html
src/mreorg/curator/frontend/templates/simulation_output_summaries.html
src/mreorg/curator/frontend/templates/simulation_run_details.html
