Metadata-Version: 1.1
Name: mreorg
Version: 0.2.0
Summary: Tools for organising and simplifying scripts for modelling
Home-page: https://github.com/mikehulluk/mreorg
Author: Mike Hull
Author-email: mikehulluk@gmail.com
License: BSD
Platform: UNKNOWN
Classifier: Development Status :: 3 - Alpha
Classifier: Topic :: Utilities
Classifier: License :: OSI Approved :: BSD License
